solar_power/__init__.py
solar_power/model.py
solar_power_prediction_tensorflow_lstm_model-0.1.1.dist-info/METADATA
solar_power_prediction_tensorflow_lstm_model-0.1.1.dist-info/WHEEL
solar_power_prediction_tensorflow_lstm_model-0.1.1.dist-info/top_level.txt
solar_power_prediction_tensorflow_lstm_model-0.1.1.dist-info/RECORD
