Metadata-Version: 2.2
Name: Solar_Power_Prediction_Tensorflow_LSTM_Model
Version: 0.1.1
Summary: A package for solar power prediction using LSTM in TensorFlow
Home-page: https://github.com/Sivatech24/AI-Driven-Solar-Energy-Management-Forecasting-Optimization-Fault-Detection
Author: CodingMaster24
Author-email: sivatech24@gmail.com
Classifier: Programming Language :: Python :: 3
Classifier: License :: OSI Approved :: MIT License
Classifier: Operating System :: OS Independent
Requires-Python: >=3.6
Requires-Dist: numpy
Requires-Dist: pandas
Requires-Dist: tensorflow
Requires-Dist: scikit-learn
Dynamic: author
Dynamic: author-email
Dynamic: classifier
Dynamic: description
Dynamic: description-content-type
Dynamic: home-page
Dynamic: requires-dist
Dynamic: requires-python
Dynamic: summary
